ejemplo/c4_tp3.vhd
library ieee;
use ieee.std_logic_1164.all;
--use ieee.std_logic_arith.all; --Es propietaria de Xilinx
--use ieee.std_logic_unsigned.all; --Es propietaria de Xilinx
--use ieee.numeric_std.all; --Ambas se reemplazan con se reemplaza con: use ieee.numeric_std.all
-- compilar con ghdl -s --std=08 --ieee=synopsys archivo.vhd si usamos las bibliotecas de Xilnx

entity c4_tp3 is
	port (C : in STD_LOGIC;
		  B : in STD_LOGIC;
		  A	: in STD_LOGIC;
		  Z : out STD_LOGIC);
end c4_tp3;

architecture RTL of c4_tp3 is

begin
	Z <= ((B and not A) or C)and(C and not A);
end RTL;

ejemplo/c4_tp3_tb.vhd
library ieee;
use ieee.std_logic_1164.all;
--use ieee.std_logic_arith.all; --Es propietaria de Xilinx
--use ieee.std_logic_unsigned.all; --Es propietaria de Xilinx
--use ieee.numeric_std.all; --Ambas se reemplazan con se reemplaza con: use ieee.numeric_std.all
-- compilar con ghdl -s --std=08 --ieee=synopsys archivo.vhd si usamos las bibliotecas de Xilnx

entity c4_tp3_TB is
end c4_tp3_TB;

architecture RTL of c4_tp3_TB is

component c4_tp3 is
	port ( A, B, C : in std_logic;
		   Z : out std_logic);
end component;

signal C, B, A, Z : STD_LOGIC := '0';

begin

dut : c4_tp3 port map(
					  C => C,
					  B => B,
					  A => A,
					  Z => Z);

Stimulus: process
begin
		C <= '0'; B <= '0'; A <='0'; wait for 100 ns;
		C <= '0'; B <= '0'; A <='1'; wait for 100 ns;
		C <= '0'; B <= '1'; A <='0'; wait for 100 ns;
		C <= '0'; B <= '1'; A <='1'; wait for 100 ns;
		C <= '1'; B <= '0'; A <='0'; wait for 100 ns;
		C <= '1'; B <= '0'; A <='1'; wait for 100 ns;
		C <= '1'; B <= '1'; A <='0'; wait for 100 ns;
		C <= '1'; B <= '1'; A <='1'; wait for 100 ns;
		wait;

end process;
end RTL;

ejemplo/c4_tp3.vcd
$date
  Wed Jun 26 20:33:52 2024
$end
$version
  GHDL v0
$end
$timescale
  1 fs
$end
$scope module standard $end
$upscope $end
$scope module std_logic_1164 $end
$upscope $end
$scope module c4_tp3_tb $end
$var reg 1 ! c $end
$var reg 1 " b $end
$var reg 1 # a $end
$var reg 1 $ z $end
$scope module dut $end
$var reg 1 % c $end
$var reg 1 & b $end
$var reg 1 ' a $end
$var reg 1 ( z $end
$upscope $end
$upscope $end
$enddefinitions $end
#0
0!
0"
0#
0$
0%
0&
0'
0(
#100000000
1#
1'
#200000000
1"
0#
1&
0'
#300000000
1#
1'
#400000000
1!
0"
0#
1$
1%
0&
0'
1(
#500000000
1#
0$
1'
0(
#600000000
1"
0#
1$
1&
0'
1(
#700000000
1#
0$
1'
0(
