ejemplo/c5_ej1.vhdl
-- generated by Digital. Don't modify this file!
-- Any changes will be lost if this file is regenerated.

LIBRARY ieee;
USE ieee.std_logic_1164.all;
USE ieee.numeric_std.all;

entity c5_ej1 is
  port (
    d: in std_logic;
    c: in std_logic;
    b: in std_logic;
    a: in std_logic;
    z: out std_logic);
end c5_ej1;

architecture Behavioral of c5_ej1 is
begin
  z <= ((NOT a AND c) XOR (NOT (NOT b AND c) OR d));
end Behavioral;

ejemplo/c5_ej1_Testbench_tb.vhdl
--  A testbench for c5_ej1_Testbench_tb
LIBRARY ieee;
USE ieee.std_logic_1164.all;
USE ieee.numeric_std.all;

entity c5_ej1_Testbench_tb is
end c5_ej1_Testbench_tb;

architecture behav of c5_ej1_Testbench_tb is
  component c5_ej1
    port (
      d: in std_logic;
      c: in std_logic;
      b: in std_logic;
      a: in std_logic;
      z: out std_logic);
  end component;

  signal d : std_logic;
  signal c : std_logic;
  signal b : std_logic;
  signal a : std_logic;
  signal z : std_logic;
  function to_string ( a: std_logic_vector) return string is
      variable b : string (1 to a'length) := (others => NUL);
      variable stri : integer := 1; 
  begin
      for i in a'range loop
          b(stri) := std_logic'image(a((i)))(2);
      stri := stri+1;
      end loop;
      return b;
  end function;
begin
  c5_ej1_0 : c5_ej1 port map (
    d => d,
    c => c,
    b => b,
    a => a,
    z => z );
  process
    type pattern_type is record
      d : std_logic;
      c : std_logic;
      b : std_logic;
      a : std_logic;
      z : std_logic;
    end record;
    type pattern_array is array (natural range <>) of pattern_type;
    constant patterns : pattern_array := (
      ('0', '0', '0', '0', '1'), -- i=0
      ('0', '0', '0', '1', '1'), -- i=1
      ('0', '0', '1', '0', '1'), -- i=2
      ('0', '0', '1', '1', '1'), -- i=3
      ('0', '1', '0', '0', '1'), -- i=4
      ('0', '1', '0', '1', '0'), -- i=5
      ('0', '1', '1', '0', '0'), -- i=6
      ('0', '1', '1', '1', '1'), -- i=7
      ('1', '0', '0', '0', '1'), -- i=8
      ('1', '0', '0', '1', '1'), -- i=9
      ('1', '0', '1', '0', '1'), -- i=10
      ('1', '0', '1', '1', '1'), -- i=11
      ('1', '1', '0', '0', '0'), -- i=12
      ('1', '1', '0', '1', '1'), -- i=13
      ('1', '1', '1', '0', '0'), -- i=14
      ('1', '1', '1', '1', '1'));
  begin
    for i in patterns'range loop
      d <= patterns(i).d;
      c <= patterns(i).c;
      b <= patterns(i).b;
      a <= patterns(i).a;
      wait for 10 ns;
      assert std_match(z, patterns(i).z) OR (z = 'Z' AND patterns(i).z = 'Z')
        report "wrong value for z, i=" & integer'image(i)
         & ", expected " & std_logic'image(patterns(i).z) & ", found " & std_logic'image(z) severity error;end loop;
    wait;
  end process;
end behav;

ejemplo/c5_ej1.vcd
$date
  Thu Jun 27 17:03:42 2024
$end
$version
  GHDL v0
$end
$timescale
  1 fs
$end
$scope module standard $end
$upscope $end
$scope module std_logic_1164 $end
$upscope $end
$scope module numeric_std $end
$upscope $end
$scope module c5_ej1_testbench_tb $end
$var reg 1 ! d $end
$var reg 1 " c $end
$var reg 1 # b $end
$var reg 1 $ a $end
$var reg 1 % z $end
$scope module c5_ej1_0 $end
$var reg 1 & d $end
$var reg 1 ' c $end
$var reg 1 ( b $end
$var reg 1 ) a $end
$var reg 1 * z $end
$upscope $end
$upscope $end
$enddefinitions $end
#0
0!
0"
0#
0$
1%
0&
0'
0(
0)
1*
#10000000
1$
1)
#20000000
1#
0$
1(
0)
#30000000
1$
1)
#40000000
1"
0#
0$
1'
0(
0)
#50000000
1$
0%
1)
0*
#60000000
1#
0$
1(
0)
#70000000
1$
1%
1)
1*
#80000000
1!
0"
0#
0$
1&
0'
0(
0)
#90000000
1$
1)
#100000000
1#
0$
1(
0)
#110000000
1$
1)
#120000000
1"
0#
0$
0%
1'
0(
0)
0*
#130000000
1$
1%
1)
1*
#140000000
1#
0$
0%
1(
0)
0*
#150000000
1$
1%
1)
1*
