ejemplo/Funcion_Boole.vhd
library IEEE;
use IEEE.STD_LOGIC_1164.ALL;
--use	IEEE.STD_LOGIC_ARITH.ALL;
--use IEEE.STD_LOGIC_UNSIGNED.ALL;

entity Funcion_Boole is
	port (C : in STD_LOGIC;
		  B	: in STD_LOGIC;
		  A	: in STD_LOGIC;
		  Z : out STD_LOGIC);
end Funcion_Boole;

architecture RTL of Funcion_Boole is

begin

	Z <= (not B and A) or (not C and A) or (C and B and not A);
	
end RTL;

ejemplo/Funcion_Boole_tb.vhd
library IEEE;
use IEEE.STD_LOGIC_1164.ALL;
--use	IEEE.STD_LOGIC_ARITH.ALL;
--use IEEE.STD_LOGIC_UNSIGNED.ALL;

entity Funcion_Boole_tb is
end Funcion_Boole_tb;

architecture RTL of Funcion_Boole_tb is

component Funcion_Boole is
	port (C : in STD_LOGIC;
		  B	: in STD_LOGIC;
		  A	: in STD_LOGIC;
		  Z : out STD_LOGIC);
end component;

signal B, A, C, Z : STD_LOGIC := '0';

begin

BOOLE : Funcion_Boole port map(
							  C => C,
							  B => B,
							  A => A,
							  Z => Z);

Stimulus: process
begin
		C <= '0'; B <= '0'; A <='0'; wait for 100 ns;
		C <= '0'; B <= '0'; A <='1'; wait for 100 ns;
		C <= '0'; B <= '1'; A <='0'; wait for 100 ns;
		C <= '0'; B <= '1'; A <='1'; wait for 100 ns;
		C <= '1'; B <= '0'; A <='0'; wait for 100 ns;
		C <= '1'; B <= '0'; A <='1'; wait for 100 ns;
		C <= '1'; B <= '1'; A <='0'; wait for 100 ns;
		C <= '1'; B <= '1'; A <='1'; wait for 100 ns;
		wait;

end process;
end RTL;

ejemplo/Funcion_Boole.vcd
$date
  Fri Jun 21 22:58:20 2024
$end
$version
  GHDL v0
$end
$timescale
  1 fs
$end
$scope module standard $end
$upscope $end
$scope module std_logic_1164 $end
$upscope $end
$scope module funcion_boole_tb $end
$var reg 1 ! b $end
$var reg 1 " a $end
$var reg 1 # c $end
$var reg 1 $ z $end
$scope module boole $end
$var reg 1 % c $end
$var reg 1 & b $end
$var reg 1 ' a $end
$var reg 1 ( z $end
$upscope $end
$upscope $end
$enddefinitions $end
#0
0!
0"
0#
0$
0%
0&
0'
0(
#100000000
1"
1$
1'
1(
#200000000
1!
0"
0$
1&
0'
0(
#300000000
1"
1$
1'
1(
#400000000
0!
0"
1#
0$
1%
0&
0'
0(
#500000000
1"
1$
1'
1(
#600000000
1!
0"
1&
0'
#700000000
1"
0$
1'
0(
