ejemplo/Funcion_Simplificada_cero.vhd
library ieee;
use ieee.std_logic_1164.all;
--use ieee.std_logic_arith.all;
--use ieee.std_logic_unsigned.all;

entity Funcion_Simplificada_cero is
	port ( A, B, C : in std_logic;
		   Y : out std_logic);
end Funcion_Simplificada_cero;

architecture Behavioral of Funcion_Simplificada_cero is

begin
	Y <= not( (not (C and not b)) and (not (B and not A)) and (not (not C and B)));
end Behavioral;

ejemplo/Funcion_Simplificada_cero_tb.vhd
library IEEE;
use IEEE.Std_logic_1164.all;
--use IEEE.Numeric_Std.all;

entity Funcion_Simplificada_cero_tb is
end;

architecture bench of Funcion_Simplificada_cero_tb is

  component Funcion_Simplificada_cero
  	port ( A, B, C : in std_logic;
  		   Y : out std_logic);
  end component;

  signal A, B, C: std_logic;
  signal Y: std_logic;

begin

  uut: Funcion_Simplificada_cero port map ( A => A,
                                       B => B,
                                       C => C,
                                       Y => Y );

  stimulus: process
  begin
  
    -- Put initialisation code here
		
		C <= '0'; B <= '0'; A <='0'; wait for 100 ns;
		C <= '0'; B <= '0'; A <='1'; wait for 100 ns;
		C <= '0'; B <= '1'; A <='0'; wait for 100 ns;
		C <= '0'; B <= '1'; A <='1'; wait for 100 ns;
		C <= '1'; B <= '0'; A <='0'; wait for 100 ns;
		C <= '1'; B <= '0'; A <='1'; wait for 100 ns;
		C <= '1'; B <= '1'; A <='0'; wait for 100 ns;
		C <= '1'; B <= '1'; A <='1'; wait for 100 ns;
		wait;

    -- Put test bench stimulus code here

    wait;
  end process;


end;

ejemplo/Funcion_Simplificada_cero_tb.vcd
$date
  Sat Jun 22 12:25:57 2024
$end
$version
  GHDL v0
$end
$timescale
  1 fs
$end
$scope module standard $end
$upscope $end
$scope module std_logic_1164 $end
$upscope $end
$scope module funcion_simplificada_cero_tb $end
$var reg 1 ! a $end
$var reg 1 " b $end
$var reg 1 # c $end
$var reg 1 $ y $end
$scope module uut $end
$var reg 1 % a $end
$var reg 1 & b $end
$var reg 1 ' c $end
$var reg 1 ( y $end
$upscope $end
$upscope $end
$enddefinitions $end
#0
0!
0"
0#
0$
0%
0&
0'
0(
#100000000
1!
1%
#200000000
0!
1"
1$
0%
1&
1(
#300000000
1!
1%
#400000000
0!
0"
1#
0%
0&
1'
#500000000
1!
1%
#600000000
0!
1"
0%
1&
#700000000
1!
0$
1%
0(
