ejemplo/GeneradordeParidad_4Ent.vhd
library ieee;
use ieee.std_logic_1164.all;
--use ieee.std_logic_arith.all;
--use ieee.std_logic_unsigned.all;

entity GeneradordeParidad_4Ent is
	port ( A, B, C, D : in std_logic;
		   Pp : out std_logic);
end GeneradordeParidad_4Ent;

architecture Behavioral of GeneradordeParidad_4Ent is

begin
	Pp <= D xor C xor B xor A;
end Behavioral;

ejemplo/GeneradordeParidad_4Ent_tb.vhd
library IEEE;
use IEEE.STD_LOGIC_1164.ALL;
--use	IEEE.STD_LOGIC_ARITH.ALL;
--use IEEE.STD_LOGIC_UNSIGNED.ALL;

entity GeneradordeParidad_4Ent_tb is
end GeneradordeParidad_4Ent_tb;

architecture RTL of GeneradordeParidad_4Ent_tb is

component GeneradordeParidad_4Ent is
	port ( A, B, C, D : in std_logic;
		   Pp : out std_logic);
end component;

signal D, C, B, A, Pp : STD_LOGIC := '0';

begin

dut : GeneradordeParidad_4Ent port map(
							  D => D,
							  C => C,
							  B => B,
							  A => A,
							  Pp => Pp);

Stimulus: process
begin
		D <= '0'; C <= '0'; B <= '0'; A <='0'; wait for 100 ns;
		D <= '0'; C <= '0'; B <= '0'; A <='1'; wait for 100 ns;
		D <= '0'; C <= '0'; B <= '1'; A <='0'; wait for 100 ns;
		D <= '0'; C <= '0'; B <= '1'; A <='1'; wait for 100 ns;
		D <= '0'; C <= '1'; B <= '0'; A <='0'; wait for 100 ns;
		D <= '0'; C <= '1'; B <= '0'; A <='1'; wait for 100 ns;
		D <= '0'; C <= '1'; B <= '1'; A <='0'; wait for 100 ns;
		D <= '0'; C <= '1'; B <= '1'; A <='1'; wait for 100 ns;
		D <= '1'; C <= '0'; B <= '0'; A <='0'; wait for 100 ns;
		D <= '1'; C <= '0'; B <= '0'; A <='1'; wait for 100 ns;
		D <= '1'; C <= '0'; B <= '1'; A <='0'; wait for 100 ns;
		D <= '1'; C <= '0'; B <= '1'; A <='1'; wait for 100 ns;
		D <= '1'; C <= '1'; B <= '0'; A <='0'; wait for 100 ns;
		D <= '1'; C <= '1'; B <= '0'; A <='1'; wait for 100 ns;
		D <= '1'; C <= '1'; B <= '1'; A <='0'; wait for 100 ns;
		D <= '1'; C <= '1'; B <= '1'; A <='1'; wait for 100 ns;
		wait;

end process;
end RTL;

ejemplo/GeneradordeParidad_4Ent_tb.vcd
$date
  Sat Jun 22 12:55:56 2024
$end
$version
  GHDL v0
$end
$timescale
  1 fs
$end
$scope module standard $end
$upscope $end
$scope module std_logic_1164 $end
$upscope $end
$scope module generadordeparidad_4ent_tb $end
$var reg 1 ! d $end
$var reg 1 " c $end
$var reg 1 # b $end
$var reg 1 $ a $end
$var reg 1 % pp $end
$scope module dut $end
$var reg 1 & a $end
$var reg 1 ' b $end
$var reg 1 ( c $end
$var reg 1 ) d $end
$var reg 1 * pp $end
$upscope $end
$upscope $end
$enddefinitions $end
#0
0!
0"
0#
0$
0%
0&
0'
0(
0)
0*
#100000000
1$
1%
1&
1*
#200000000
1#
0$
0&
1'
#300000000
1$
0%
1&
0*
#400000000
1"
0#
0$
1%
0&
0'
1(
1*
#500000000
1$
0%
1&
0*
#600000000
1#
0$
0&
1'
#700000000
1$
1%
1&
1*
#800000000
1!
0"
0#
0$
0&
0'
0(
1)
#900000000
1$
0%
1&
0*
#1000000000
1#
0$
0&
1'
#1100000000
1$
1%
1&
1*
#1200000000
1"
0#
0$
0%
0&
0'
1(
0*
#1300000000
1$
1%
1&
1*
#1400000000
1#
0$
0&
1'
#1500000000
1$
0%
1&
0*
