ejemplo/mux2c.vhd
library ieee;
use ieee.std_logic_1164.all;
--use ieee.std_logic_arith.all;
--use ieee.std_logic_unsigned.all;

entity mux2c is
	port ( C, B, A : in std_logic;
		   Y : out std_logic);
end mux2c;

architecture Behavioral of mux2c is

begin
	Y <= (not C and A) or (C and B);
end Behavioral;

ejemplo/mux2c_tb.vhd
library IEEE;
use IEEE.STD_LOGIC_1164.ALL;
--use	IEEE.STD_LOGIC_ARITH.ALL;
--use IEEE.STD_LOGIC_UNSIGNED.ALL;

entity mux2c_tb is
end mux2c_tb;

architecture RTL of mux2c_tb is

component mux2c is
	port ( C, B, A : in std_logic;
		   Y : out std_logic);
end component;

signal C, B, A, Y : STD_LOGIC := '0';

begin

dut : mux2c port map(
					  C => C,
					  B => B,
					  A => A,
					  Y => Y);

Stimulus: process
begin
		C <= '0'; B <= '0'; A <='0'; wait for 100 ns;
		C <= '0'; B <= '0'; A <='1'; wait for 100 ns;
		C <= '0'; B <= '1'; A <='0'; wait for 100 ns;
		C <= '0'; B <= '1'; A <='1'; wait for 100 ns;
		C <= '1'; B <= '0'; A <='0'; wait for 100 ns;
		C <= '1'; B <= '0'; A <='1'; wait for 100 ns;
		C <= '1'; B <= '1'; A <='0'; wait for 100 ns;
		C <= '1'; B <= '1'; A <='1'; wait for 100 ns;
		wait;

end process;
end RTL;

ejemplo/mux2c.vcd
$date
  Sat Jun 22 14:01:06 2024
$end
$version
  GHDL v0
$end
$timescale
  1 fs
$end
$scope module standard $end
$upscope $end
$scope module std_logic_1164 $end
$upscope $end
$scope module mux2c_tb $end
$var reg 1 ! c $end
$var reg 1 " b $end
$var reg 1 # a $end
$var reg 1 $ y $end
$scope module dut $end
$var reg 1 % c $end
$var reg 1 & b $end
$var reg 1 ' a $end
$var reg 1 ( y $end
$upscope $end
$upscope $end
$enddefinitions $end
#0
0!
0"
0#
0$
0%
0&
0'
0(
#100000000
1#
1$
1'
1(
#200000000
1"
0#
0$
1&
0'
0(
#300000000
1#
1$
1'
1(
#400000000
1!
0"
0#
0$
1%
0&
0'
0(
#500000000
1#
1'
#600000000
1"
0#
1$
1&
0'
1(
#700000000
1#
1'
