ejemplo/MUX_Senales.vhd
library ieee;
use ieee.std_logic_1164.all;
--use ieee.std_logic_arith.all;
--use ieee.std_logic_unsigned.all;

entity MUX_Senales is
	port ( B, A, C : in std_logic;
		   Y : out std_logic);
end MUX_Senales;

architecture Behavioral of MUX_Senales is

Signal Y1, Y2 :  std_logic; --Describo todas las señales
begin
	Y <= Y1 or Y2;
	Y1 <= not C and A;
	Y2 <= C and B;
	-- Las 3 asignaciones simples se ejecutan al mismo tiempo
end Behavioral;

ejemplo/MUX_Senales_tb.vhd
library IEEE;
use IEEE.STD_LOGIC_1164.ALL;
--use	IEEE.STD_LOGIC_ARITH.ALL;
--use IEEE.STD_LOGIC_UNSIGNED.ALL;

entity MUX_Senales_TB is
end MUX_Senales_TB;

architecture Behavioral of MUX_Senales_TB is

component MUX_Senales is
	port ( A, B, C : in std_logic;
		   Y : out std_logic);
end component;

signal C, B, A, Y : STD_LOGIC := '0';

begin

dut : MUX_Senales port map(
					  C => C,
					  B => B,
					  A => A,
					  Y => Y);

Stimulus: process
begin
		C <= '0'; B <= '0'; A <='0'; wait for 100 ns;
		C <= '0'; B <= '0'; A <='1'; wait for 100 ns;
		C <= '0'; B <= '1'; A <='0'; wait for 100 ns;
		C <= '0'; B <= '1'; A <='1'; wait for 100 ns;
		C <= '1'; B <= '0'; A <='0'; wait for 100 ns;
		C <= '1'; B <= '0'; A <='1'; wait for 100 ns;
		C <= '1'; B <= '1'; A <='0'; wait for 100 ns;
		C <= '1'; B <= '1'; A <='1'; wait for 100 ns;
		wait;

end process;
end Behavioral;

ejemplo/MUX_Senales_tb.vcd
$date
  Sat Jun 22 15:42:12 2024
$end
$version
  GHDL v0
$end
$timescale
  1 fs
$end
$scope module standard $end
$upscope $end
$scope module std_logic_1164 $end
$upscope $end
$scope module mux_senales_tb $end
$var reg 1 ! c $end
$var reg 1 " b $end
$var reg 1 # a $end
$var reg 1 $ y $end
$scope module dut $end
$var reg 1 % b $end
$var reg 1 & a $end
$var reg 1 ' c $end
$var reg 1 ( y $end
$var reg 1 ) y1 $end
$var reg 1 * y2 $end
$upscope $end
$upscope $end
$enddefinitions $end
#0
0!
0"
0#
0$
0%
0&
0'
0(
0)
0*
#100000000
1#
1$
1&
1(
1)
#200000000
1"
0#
0$
1%
0&
0(
0)
#300000000
1#
1$
1&
1(
1)
#400000000
1!
0"
0#
0$
0%
0&
1'
0(
0)
#500000000
1#
1&
#600000000
1"
0#
1$
1%
0&
1(
1*
#700000000
1#
1&
