ejemplo/Pepe.vhd
library ieee;
use ieee.std_logic_1164.all;
--use ieee.std_logic_arith.all;
--use ieee.std_logic_unsigned.all;

entity Pepe is
	port ( D, C, B, A : in std_logic;
		   Q, S : out std_logic);
end Pepe;

architecture Behavioral of Pepe is

begin
	Q <= D or C;
	S <= B and A;
end Behavioral;

ejemplo/Pepe_tb.vhd
library IEEE;
use IEEE.STD_LOGIC_1164.ALL;
--use	IEEE.STD_LOGIC_ARITH.ALL;
--use IEEE.STD_LOGIC_UNSIGNED.ALL;

entity Pepe_tb is
end Pepe_tb;

architecture Bahavioral of Pepe_tb is

component Pepe is
	port ( D, C, B, A : in std_logic;
		   Q, S : out std_logic);
end component;

signal D, C, B, A, Q, S : STD_LOGIC := '0';

begin

dut : Pepe port map(
					  D => D,
					  C => C,
					  B => B,
					  A => A,
					  Q => Q,
					  S => S);

Stimulus: process
begin
		D <= '0'; C <= '0'; B <= '0'; A <='0'; wait for 100 ns;
		D <= '0'; C <= '0'; B <= '0'; A <='1'; wait for 100 ns;
		D <= '0'; C <= '0'; B <= '1'; A <='0'; wait for 100 ns;
		D <= '0'; C <= '0'; B <= '1'; A <='1'; wait for 100 ns;
		D <= '0'; C <= '1'; B <= '0'; A <='0'; wait for 100 ns;
		D <= '0'; C <= '1'; B <= '0'; A <='1'; wait for 100 ns;
		D <= '0'; C <= '1'; B <= '1'; A <='0'; wait for 100 ns;
		D <= '0'; C <= '1'; B <= '1'; A <='1'; wait for 100 ns;
		D <= '1'; C <= '0'; B <= '0'; A <='0'; wait for 100 ns;
		D <= '1'; C <= '0'; B <= '0'; A <='1'; wait for 100 ns;
		D <= '1'; C <= '0'; B <= '1'; A <='0'; wait for 100 ns;
		D <= '1'; C <= '0'; B <= '1'; A <='1'; wait for 100 ns;
		D <= '1'; C <= '1'; B <= '0'; A <='0'; wait for 100 ns;
		D <= '1'; C <= '1'; B <= '0'; A <='1'; wait for 100 ns;
		D <= '1'; C <= '1'; B <= '1'; A <='0'; wait for 100 ns;
		D <= '1'; C <= '1'; B <= '1'; A <='1'; wait for 100 ns;
		wait;

end process;
end Bahavioral;

ejemplo/Pepe_tb.vcd
$date
  Sat Jun 22 14:47:12 2024
$end
$version
  GHDL v0
$end
$timescale
  1 fs
$end
$scope module standard $end
$upscope $end
$scope module std_logic_1164 $end
$upscope $end
$scope module pepe_tb $end
$var reg 1 ! d $end
$var reg 1 " c $end
$var reg 1 # b $end
$var reg 1 $ a $end
$var reg 1 % q $end
$var reg 1 & s $end
$scope module dut $end
$var reg 1 ' d $end
$var reg 1 ( c $end
$var reg 1 ) b $end
$var reg 1 * a $end
$var reg 1 + q $end
$var reg 1 , s $end
$upscope $end
$upscope $end
$enddefinitions $end
#0
0!
0"
0#
0$
0%
0&
0'
0(
0)
0*
0+
0,
#100000000
1$
1*
#200000000
1#
0$
1)
0*
#300000000
1$
1&
1*
1,
#400000000
1"
0#
0$
1%
0&
1(
0)
0*
1+
0,
#500000000
1$
1*
#600000000
1#
0$
1)
0*
#700000000
1$
1&
1*
1,
#800000000
1!
0"
0#
0$
0&
1'
0(
0)
0*
0,
#900000000
1$
1*
#1000000000
1#
0$
1)
0*
#1100000000
1$
1&
1*
1,
#1200000000
1"
0#
0$
0&
1(
0)
0*
0,
#1300000000
1$
1*
#1400000000
1#
0$
1)
0*
#1500000000
1$
1&
1*
1,
